jejudo/__init__.py
jejudo/_version.py
jejudo/exception_handling.py
jejudo/flags.py
jejudo/functools.py
jejudo/hljs.py
jejudo/modules.py
jejudo/paginators.py
jejudo/shell.py
jejudo/core/__init__.py
jejudo/core/codeblocks.py
jejudo/core/jeju_log.py
jejudo/core/jejudo.py
jejudo/core/shim/__init__.py
jejudo/core/shim/paginator_170.py
jejudo/core/shim/paginator_200.py
jejudo/core/shim/paginator_base.py
jejudo/core/work/__init__.py
jejudo/core/work/types.py
jejudo/repl/__init__.py
jejudo/repl/compilation.py
jejudo/repl/disassembly.py
jejudo/repl/inspections.py
jejudo/repl/repl_builtins.py
jejudo/repl/scope.py
jejudo/repl/walkers.py
jejudo-2.7.5.dist-info/METADATA
jejudo-2.7.5.dist-info/WHEEL
jejudo-2.7.5.dist-info/top_level.txt
jejudo-2.7.5.dist-info/RECORD
